pyphy/__init__.py
pyphy/body.py
pyphy/boundingbox.py
pyphy/collision_manifold.py
pyphy/pygame_integration.py
pyphy/pyphymath.py
pyphy/sample.py
pyphy/transform.py
pyphy/vector2.py
pyphy/world.py
pyphy2D-2.dist-info/LICENSE
pyphy2D-2.dist-info/METADATA
pyphy2D-2.dist-info/WHEEL
pyphy2D-2.dist-info/top_level.txt
pyphy2D-2.dist-info/RECORD
