Metadata-Version: 2.1
Name: pyphy2D
Version: 2
Summary: A 2D Rigid Body Physics Engine.
Author: Krishiv Goel
Author-email: KrishivGoelXD@gmail.com
Classifier: Programming Language :: Python :: 3
Classifier: License :: OSI Approved :: MIT License
Classifier: Operating System :: OS Independent
Requires-Python: >=3.6
License-File: LICENSE
Requires-Dist: pygame
